setup.cfg
setup.py
pylama_print/__init__.py
pylama_print/linter_print.py
pylama_print.egg-info/PKG-INFO
pylama_print.egg-info/SOURCES.txt
pylama_print.egg-info/dependency_links.txt
pylama_print.egg-info/entry_points.txt
pylama_print.egg-info/not-zip-safe
pylama_print.egg-info/top_level.txt
pylama_print/tests/__init__.py
pylama_print/tests/test_linter.py