Metadata-Version: 1.0
Name: pylama-print
Version: 1.0
Summary: A super-simple pylama linter to flag print() calls
Home-page: https://github.com/GeoTob/pylama_print
Author: Tobias Schulmann
Author-email: no@ema.il
License: UNKNOWN
Platform: UNKNOWN
